<?xml version="1.0" encoding="UTF-8"?>
<record_update table="sysevent_register">
    <sysevent_register action="INSERT_OR_UPDATE">
        <description>This Event will be triggered for the consultants who haven't submitted timesheets</description>
        <event_name>x_nykl3_tenroxnbsa.consultant.ts.remind</event_name>
        <fired_by/>
        <queue/>
        <suffix>consultant.ts.remind</suffix>
        <sys_class_name>sysevent_register</sys_class_name>
        <sys_created_by>GARGL</sys_created_by>
        <sys_created_on>2017-11-08 19:09:26</sys_created_on>
        <sys_customer_update>true</sys_customer_update>
        <sys_id>c64a86310f9a43001416d23be1050eb3</sys_id>
        <sys_mod_count>2</sys_mod_count>
        <sys_name>x_nykl3_tenroxnbsa.consultant.ts.remind</sys_name>
        <sys_package display_value="TenroxNBSA" source="x_nykl3_tenroxnbsa">1a0e09cc0f4332001416d23be1050e3f</sys_package>
        <sys_policy/>
        <sys_replace_on_upgrade>false</sys_replace_on_upgrade>
        <sys_scope display_value="TenroxNBSA">1a0e09cc0f4332001416d23be1050e3f</sys_scope>
        <sys_update_name>sysevent_register_c64a86310f9a43001416d23be1050eb3</sys_update_name>
        <sys_updated_by>GARGL</sys_updated_by>
        <sys_updated_on>2018-04-29 03:08:35</sys_updated_on>
        <table>x_nykl3_tenroxnbsa_timesheet</table>
    </sysevent_register>
</record_update>
